cheesymamas/__init__.py
cheesymamas/cheesymamas.py
cheesymamas/main.py
cheesymamas/assets/CheesyMamas.png
cheesymamas-0.2.73.dist-info/METADATA
cheesymamas-0.2.73.dist-info/WHEEL
cheesymamas-0.2.73.dist-info/entry_points.txt
cheesymamas-0.2.73.dist-info/top_level.txt
cheesymamas-0.2.73.dist-info/RECORD
