Metadata-Version: 2.4
Name: cheesymamas
Version: 0.2.73
Summary: A local-first code editor with cheesy Git goodness
Author: Luke Miller
Classifier: Programming Language :: Python :: 3
Classifier: Environment :: X11 Applications :: Qt
Classifier: Intended Audience :: Developers
Classifier: License :: OSI Approved :: MIT License
Classifier: Operating System :: POSIX :: Linux
Classifier: Topic :: Text Editors :: Integrated Development Environments (IDE)
Requires-Python: >=3.8
Requires-Dist: PyQt6>=6.0.0
Requires-Dist: importlib-resources; python_version < "3.9"
Dynamic: author
Dynamic: classifier
Dynamic: description
Dynamic: description-content-type
Dynamic: requires-dist
Dynamic: requires-python
Dynamic: summary
